faas/__init__.py
pyfaas-0.3.1.dist-info/WHEEL
pyfaas-0.3.1.dist-info/METADATA
pyfaas-0.3.1.dist-info/RECORD
