Metadata-Version: 2.1
Name: pyfaas
Version: 0.3.1
Summary: Python client for Fluent as a Server
Author: AlwinW
Author-email: 16846521+alwinw@users.noreply.github.com
Requires-Python: >=3.8,<4.0
Classifier: Programming Language :: Python :: 3
Classifier: Programming Language :: Python :: 3.10
Classifier: Programming Language :: Python :: 3.8
Classifier: Programming Language :: Python :: 3.9
